LICENSE
README.md
pyproject.toml
setup.cfg
src/aai_face_search_db_builder_test.egg-info/PKG-INFO
src/aai_face_search_db_builder_test.egg-info/SOURCES.txt
src/aai_face_search_db_builder_test.egg-info/dependency_links.txt
src/aai_face_search_db_builder_test.egg-info/entry_points.txt
src/aai_face_search_db_builder_test.egg-info/requires.txt
src/aai_face_search_db_builder_test.egg-info/top_level.txt
src/db_builder/__init__.py
src/db_builder/db_builder.py