Metadata-Version: 2.1
Name: aai-face-search-db-builder-test
Version: 0.0.1
Summary: A simple CLI script to call Face Search DB Build API
Home-page: UNKNOWN
Author: AAI On-prem
License: UNKNOWN
Platform: UNKNOWN
Classifier: Programming Language :: Python :: 3
Classifier: License :: OSI Approved :: MIT License
Classifier: Operating System :: OS Independent
Requires-Python: >=3.7
License-File: LICENSE
